dj_jsonapi-0.0.4.dist-info/DESCRIPTION.rst
dj_jsonapi-0.0.4.dist-info/METADATA
dj_jsonapi-0.0.4.dist-info/metadata.json
dj_jsonapi-0.0.4.dist-info/RECORD
dj_jsonapi-0.0.4.dist-info/top_level.txt
dj_jsonapi-0.0.4.dist-info/WHEEL
json_api/__init__.py
json_api/exceptions.py
json_api/filters.py
json_api/generics.py
json_api/inclusion.py
json_api/negotiation.py
json_api/pagination.py
json_api/parsers.py
json_api/renderers.py
json_api/routers.py
json_api/serializers.py
json_api/settings.py
json_api/views.py
json_api/viewsets.py
json_api/fantasy/__init__.py
json_api/fantasy/serializers.py
json_api/fantasy/urls.py
json_api/fantasy/views.py
json_api/mixins/__init__.py
json_api/mixins/base.py
json_api/mixins/related.py
json_api/mixins/relationships.py
json_api/utils/__init__.py
json_api/utils/model_meta.py
json_api/utils/rels.py
json_api/utils/reverse.py
json_api/utils/types.py
json_api/utils/urls.py
json_api/utils/view_meta.py
tests/mixins/__init__.py
tests/mixins/test_relationships.py
