Metadata-Version: 2.0
Name: dj-jsonapi
Version: 0.0.4
Summary: A JSON-API server implementation built for Django on top of Django Rest Framework
Home-page: https://github.com/ITNG/dj-jsonapi
Author: Ryan P Kilby
Author-email: rpkilby@ncsu.edu
License: BSD License
Platform: UNKNOWN
Classifier: Development Status :: 3 - Alpha
Classifier: Environment :: Web Environment
Classifier: Framework :: Django
Classifier: Intended Audience :: Developers
Classifier: License :: OSI Approved :: BSD License
Classifier: Operating System :: OS Independent
Classifier: Programming Language :: Python
Classifier: Programming Language :: Python :: 2.7
Classifier: Topic :: Internet :: WWW/HTTP
Classifier: Topic :: Software Development :: Libraries :: Python Modules
Requires-Dist: djangorestframework (>=3.2,<3.4,!=3.2.3)
Requires-Dist: djangorestframework-filters
